LICENSE.txt
README.md
setup.py
src/beautifullogger/__init__.py
src/beautifullogger/beautifullogger.py
src/beautifullogger.egg-info/PKG-INFO
src/beautifullogger.egg-info/SOURCES.txt
src/beautifullogger.egg-info/dependency_links.txt
src/beautifullogger.egg-info/requires.txt
src/beautifullogger.egg-info/top_level.txt