Metadata-Version: 2.1
Name: beautifullogger
Version: 4.6
Summary: A very simple log formatter for the logging module that can be used as is
Home-page: https://github.com/JulienBrn/BeautifulLogger
Download-URL: https://github.com/JulienBrn/BeautifulLogger.git
Author: Julien Braine
Author-email: julienbraine@yahoo.fr
License: MIT
Keywords: python,logging
License-File: LICENSE.txt
